xdownscale/__init__.py
xdownscale/core.py
xdownscale/distgssr.py
xdownscale/model.py
xdownscale/srresnet.py
xdownscale/swinir.py
xdownscale/utils.py
xdownscale-1.0.2.dist-info/licenses/LICENSE.rst
xdownscale-1.0.2.dist-info/METADATA
xdownscale-1.0.2.dist-info/WHEEL
xdownscale-1.0.2.dist-info/top_level.txt
xdownscale-1.0.2.dist-info/RECORD
