Metadata-Version: 2.4
Name: xdownscale
Version: 1.0.2
Summary: A PyTorch-based tool to downscale spatiotemporal data
Home-page: https://github.com/manmeet3591/xdownscale
Author: Manmeet Singh, Naveen Sudharsan
Classifier: Programming Language :: Python :: 3
Classifier: License :: OSI Approved :: MIT License
Classifier: Operating System :: OS Independent
Requires-Python: >=3.7
License-File: LICENSE.rst
Requires-Dist: torch
Requires-Dist: xarray
Requires-Dist: numpy
Dynamic: author
Dynamic: classifier
Dynamic: description
Dynamic: description-content-type
Dynamic: home-page
Dynamic: license-file
Dynamic: requires-dist
Dynamic: requires-python
Dynamic: summary
